gmlutil_ts_models/models.py
gmlutil_ts_models-2.0.3.dist-info/METADATA
gmlutil_ts_models-2.0.3.dist-info/WHEEL
gmlutil_ts_models-2.0.3.dist-info/top_level.txt
gmlutil_ts_models-2.0.3.dist-info/RECORD
