Metadata-Version: 2.1
Name: gmlutil-ts-models
Version: 2.0.3
Summary: General Machine Learning Utility Package for Timeseries Models
Home-page: https://github.com/Phillip1982/gmlutil_ts_models
Author: Phillip Kim
Author-email: phillip.kim@ejgallo.com
License: BSD 2-clause
Classifier: Development Status :: 5 - Production/Stable
Classifier: Framework :: IPython
Classifier: Intended Audience :: Developers
Classifier: License :: OSI Approved :: BSD License
Classifier: Operating System :: MacOS
Classifier: Operating System :: Microsoft :: Windows :: Windows XP
Classifier: Operating System :: POSIX :: Linux
Classifier: Programming Language :: Python :: 3.9
Classifier: Programming Language :: Python :: 3.10
Classifier: Programming Language :: Python :: 3.11
Classifier: Programming Language :: Python :: 3.12
Requires-Dist: numpy (==1.26.4)
Requires-Dist: pandas (<=2.2.2,>2.1.0)
Requires-Dist: statsmodels (>=0.14.0)
